econoplots/__init__.py
econoplots/_standalone_plotters.py
econoplots/colors.py
econoplots/converter.py
econoplots/params.py
econoplots/utils.py
econoplots-0.2.1.dist-info/LICENSE
econoplots-0.2.1.dist-info/METADATA
econoplots-0.2.1.dist-info/WHEEL
econoplots-0.2.1.dist-info/top_level.txt
econoplots-0.2.1.dist-info/RECORD
