Metadata-Version: 2.1
Name: econoplots
Version: 0.2.1
Summary: Formats Matplotlib plots into the style of The Economist
Author-email: Dylan Penn <dylan.penn@vt.edu>
License: Copyright (c) 2022 Dylan Penn
Project-URL: Homepage, https://github.com/dylan906/econoplots
Classifier: Programming Language :: Python :: 3
Classifier: License :: OSI Approved :: MIT License
Classifier: Operating System :: OS Independent
Requires-Python: >=3.7
License-File: LICENSE
Requires-Dist: numpy >=1.20
Requires-Dist: matplotlib >=3.5
Requires-Dist: black >=23.3
